pywebwinui3/__init__.py
pywebwinui3/core.py
pywebwinui3/event.py
pywebwinui3/type.py
pywebwinui3/util.py
pywebwinui3/web/index.html
pywebwinui3/web/PYWEBWINUI3/PretendardVariable.subset.0.woff2
pywebwinui3/web/PYWEBWINUI3/PretendardVariable.subset.1.woff2
pywebwinui3/web/PYWEBWINUI3/PretendardVariable.subset.10.woff2
pywebwinui3/web/PYWEBWINUI3/PretendardVariable.subset.11.woff2
pywebwinui3/web/PYWEBWINUI3/PretendardVariable.subset.12.woff2
pywebwinui3/web/PYWEBWINUI3/PretendardVariable.subset.13.woff2
pywebwinui3/web/PYWEBWINUI3/PretendardVariable.subset.14.woff2
pywebwinui3/web/PYWEBWINUI3/PretendardVariable.subset.15.woff2
pywebwinui3/web/PYWEBWINUI3/PretendardVariable.subset.16.woff2
pywebwinui3/web/PYWEBWINUI3/PretendardVariable.subset.17.woff2
pywebwinui3/web/PYWEBWINUI3/PretendardVariable.subset.18.woff2
pywebwinui3/web/PYWEBWINUI3/PretendardVariable.subset.19.woff2
pywebwinui3/web/PYWEBWINUI3/PretendardVariable.subset.2.woff2
pywebwinui3/web/PYWEBWINUI3/PretendardVariable.subset.20.woff2
pywebwinui3/web/PYWEBWINUI3/PretendardVariable.subset.21.woff2
pywebwinui3/web/PYWEBWINUI3/PretendardVariable.subset.22.woff2
pywebwinui3/web/PYWEBWINUI3/PretendardVariable.subset.23.woff2
pywebwinui3/web/PYWEBWINUI3/PretendardVariable.subset.24.woff2
pywebwinui3/web/PYWEBWINUI3/PretendardVariable.subset.25.woff2
pywebwinui3/web/PYWEBWINUI3/PretendardVariable.subset.26.woff2
pywebwinui3/web/PYWEBWINUI3/PretendardVariable.subset.27.woff2
pywebwinui3/web/PYWEBWINUI3/PretendardVariable.subset.28.woff2
pywebwinui3/web/PYWEBWINUI3/PretendardVariable.subset.29.woff2
pywebwinui3/web/PYWEBWINUI3/PretendardVariable.subset.3.woff2
pywebwinui3/web/PYWEBWINUI3/PretendardVariable.subset.30.woff2
pywebwinui3/web/PYWEBWINUI3/PretendardVariable.subset.31.woff2
pywebwinui3/web/PYWEBWINUI3/PretendardVariable.subset.32.woff2
pywebwinui3/web/PYWEBWINUI3/PretendardVariable.subset.33.woff2
pywebwinui3/web/PYWEBWINUI3/PretendardVariable.subset.34.woff2
pywebwinui3-1.0.0b39.dist-info/licenses/LICENSE
pywebwinui3-1.0.0b39.dist-info/licenses/NOTICE
pywebwinui3-1.0.0b39.dist-info/METADATA
pywebwinui3-1.0.0b39.dist-info/WHEEL
pywebwinui3-1.0.0b39.dist-info/top_level.txt
pywebwinui3-1.0.0b39.dist-info/RECORD
