Metadata-Version: 2.4
Name: PyWebWinUI3
Version: 1.0.0b39
Summary: Create modern WinUI3-style desktop UIs in Python effortlessly using pywebview.
Home-page: https://github.com/Haruna5718/PyWebWinUI3
Author: Haruna5718
Author-email: me@haruna5718.dev
License: Apache 2.0
Keywords: PyWebWinUI3,pywebwinui3,Haruna5718,pywebview,winui3,pypi
License-File: LICENSE
License-File: NOTICE
Requires-Dist: pywebview
Requires-Dist: pywin32
Dynamic: author
Dynamic: author-email
Dynamic: description
Dynamic: description-content-type
Dynamic: home-page
Dynamic: keywords
Dynamic: license
Dynamic: license-file
Dynamic: requires-dist
Dynamic: summary
